fromBK/sv_class/D_FF/d_flip_flop.v
module d_flip_flop_sync_reset (

    input wire clk,

    input wire rst, // Synchronous reset

    input wire d,

    output reg q

);



always @(posedge clk) begin

    if (rst) begin

        q <= 1'b0; // Reset Q to 0

    end else begin

        q <= d;    // Load data 'd' into Q on clock edge

    end

end



endmodule

fromBK/sv_class/D_FF/d_ff_tb.v
module d_ff_tb;

  // Declare signals for inputs and outputs of the DUT

  reg d;        // Data input
  reg clk;      // Clock input
  reg rst;    // Active-high reset input
  wire q;       // Data output

  // Instantiate the D flip-flop module (assuming it's named 'd_ff')

  d_flip_flop_sync_reset d_flip_flop_sync_reset (
    .q(q),
    .d(d),
    .rst(rst),
    .clk(clk)
  );

  // Clock generation
  initial begin
    clk = 0;
    forever #1 clk = ~clk; // Generate a clock with a 10ns period
  end

  // Testbench initialization and stimulus application

  initial begin

    // Initialize inputs
    d = 0;
    rst = 1; // Assert reset
    #1 d = 1;  
    #1 d = 0;
    #1 d = 1;
    #1 d = 0;

    // De-assert reset and apply input changes
    #4 rst = 0;
    #1 d = 1;  // Apply D=1, Q should go high on next rising clock edge
    #1 d = 0;  // Apply D=0, Q should go low on next rising clock edge
    #1 d = 1;  // Apply D=1, Q should go high on next rising clock edge
    #1 d = 0;  // Apply D=0, Q should go low on next rising clock edge

    #10  $finish;
  end
  // Optional: Monitor signals during simulation
  initial begin
    $dumpfile("my_design.vcd");
    $dumpvars;  
    $monitor("Time=%0t, D=%b, CLK=%b, RST_N=%b, Q=%b", $time, d, clk, rst, q);
  end

endmodule

fromBK/sv_class/D_FF/my_design.vcd
$date
	Thu Sep 11 15:41:51 2025
$end
$version
	Icarus Verilog
$end
$timescale
	1s
$end
$scope module d_ff_tb $end
$var wire 1 ! q $end
$var reg 1 " clk $end
$var reg 1 # d $end
$var reg 1 $ rst $end
$scope module d_flip_flop_sync_reset $end
$var wire 1 " clk $end
$var wire 1 # d $end
$var wire 1 $ rst $end
$var reg 1 ! q $end
$upscope $end
$upscope $end
$enddefinitions $end
#0
$dumpvars
1$
0#
0"
x!
$end
#1
0!
1#
1"
#2
0#
0"
#3
1#
1"
#4
0#
0"
#5
1"
#6
0"
#7
1"
#8
0"
0$
#9
1!
1"
1#
#10
0"
0#
#11
1"
1#
#12
0"
0#
#13
0!
1"
