fromBK/sv_class/DEMUX_1to8/demux_1to8.v
module demux_1_to_8 (
    input wire data_in,
    input wire [2:0] sel,
    output reg [7:0] data_out
);

    always @(*) begin

        // Initialize all outputs to 0
        data_out = 8'b00000000; 

        // Assign data_in to the selected output based on 'sel'
        case (sel)
            3'b000: data_out[0] = data_in;
            3'b001: data_out[1] = data_in;
            3'b010: data_out[2] = data_in;
            3'b011: data_out[3] = data_in;
            3'b100: data_out[4] = data_in;
            3'b101: data_out[5] = data_in;
            3'b110: data_out[6] = data_in;
            3'b111: data_out[7] = data_in;
            default: data_out = 8'b00000000; // Handle X or Z on select lines
        endcase
    end

endmodule

fromBK/sv_class/DEMUX_1to8/tb_demux_1to8.v
module tb_demux_1_to_8;

    // Declare signals for the demux
    reg data_in_tb;
    reg [2:0] sel_tb;
    wire [7:0] data_out_tb;

    // Instantiate the demux module
    demux_1_to_8 uut (
        .data_in(data_in_tb),
        .sel(sel_tb),
        .data_out(data_out_tb)
    );

    initial begin

        // Dump variables for waveform viewing
        $dumpfile("demux_1_to_8.vcd");
        $dumpvars(0, tb_demux_1_to_8); // Dump all signals in the current scope and below

        // Test cases
        data_in_tb = 1'b1;
        sel_tb = 3'b000; #10; // Output 0 high
        sel_tb = 3'b001; #10; // Output 1 high
        sel_tb = 3'b010; #10; // Output 2 high
        sel_tb = 3'b011; #10; // Output 3 high
        sel_tb = 3'b100; #10; // Output 4 high
        sel_tb = 3'b101; #10; // Output 5 high
        sel_tb = 3'b110; #10; // Output 6 high
        sel_tb = 3'b111; #10; // Output 7 high

        data_in_tb = 1'b0;
        sel_tb = 3'b000; #10; // All outputs low
        sel_tb = 3'b111; #10; // All outputs low

        $finish; // End simulation
    end

endmodule

fromBK/sv_class/DEMUX_1to8/demux_1_to_8.vcd
$date
	Mon Sep 22 16:30:49 2025
$end
$version
	Icarus Verilog
$end
$timescale
	1s
$end
$scope module tb_demux_1_to_8 $end
$var wire 8 ! data_out_tb [7:0] $end
$var reg 1 " data_in_tb $end
$var reg 3 # sel_tb [2:0] $end
$scope module uut $end
$var wire 1 " data_in $end
$var wire 3 $ sel [2:0] $end
$var reg 8 % data_out [7:0] $end
$upscope $end
$upscope $end
$enddefinitions $end
#0
$dumpvars
b1 %
b0 $
b0 #
1"
b1 !
$end
#10
b10 !
b10 %
b1 #
b1 $
#20
b100 !
b100 %
b10 #
b10 $
#30
b1000 !
b1000 %
b11 #
b11 $
#40
b10000 !
b10000 %
b100 #
b100 $
#50
b100000 !
b100000 %
b101 #
b101 $
#60
b1000000 !
b1000000 %
b110 #
b110 $
#70
b10000000 !
b10000000 %
b111 #
b111 $
#80
b0 !
b0 %
b0 #
b0 $
0"
#90
b111 #
b111 $
