fromBK/sv_class/priority_encoder/encoder.v
module encoder (

    input  wire [7:0] data_in,
    output reg  [2:0] encoded_out,
    output reg        valid_out
);

      always @(*)  begin

        // Default values
        encoded_out = 3'b000;
        valid_out = 1'b0;

        // Priority encoding (highest priority for data_in[7])
        if (data_in[7]) begin
            encoded_out = 3'b111;
            valid_out = 1'b1;
        end else if (data_in[6]) begin
            encoded_out = 3'b110;
            valid_out = 1'b1;
        end else if (data_in[5]) begin
            encoded_out = 3'b101;
            valid_out = 1'b1;
    	end else if (data_in[4]) begin
	    encoded_out = 3'b100;
            valid_out = 1'b1;	     
    	end else if (data_in[3]) begin
            encoded_out = 3'b011;
            valid_out = 1'b1;
        end else if (data_in[2]) begin
            encoded_out = 3'b010;
            valid_out = 1'b1;
        end else if (data_in[1]) begin
            encoded_out = 3'b001;
            valid_out = 1'b1;
        end else if (data_in[0]) begin
            encoded_out = 3'b000;
            valid_out = 1'b1;
        end else begin
            // No input asserted

            encoded_out = 3'b000; // Or 3'bx for don't care, depending on requirements
            valid_out = 1'b0;
        end
    end

endmodule

fromBK/sv_class/priority_encoder/tb_encoder.v
`timescale 1ns / 1ps

module tb_encoder;

    // Testbench signals
    reg  [7:0] tb_data_in;
    wire [2:0] tb_encoded_out;
    wire       tb_valid_out;

    // Instantiate the Device Under Test (DUT)
    encoder dut (
        .data_in     (tb_data_in),
        .encoded_out (tb_encoded_out),
        .valid_out   (tb_valid_out)
    );

    // Initial block for stimulating inputs
    initial begin
        // Initialize inputs
        tb_data_in = 8'b00000000;
        #10;

        // Test cases
        tb_data_in = 8'b00000001; // data_in[0] active
        #10;
        tb_data_in = 8'b00000010; // data_in[1] active
        #10;
        tb_data_in = 8'b00000100; // data_in[2] active
        #10;
        tb_data_in = 8'b00001000; // data_in[3] active
        #10;
        tb_data_in = 8'b00010000; // data_in[4] active
        #10;
        tb_data_in = 8'b00100000; // data_in[5] active
        #10;
        tb_data_in = 8'b01000000; // data_in[6] active
        #10;
        tb_data_in = 8'b10000000; // data_in[7] active
        #10;

        // Test with multiple inputs active (priority should be observed)
        tb_data_in = 8'b10000001; // data_in[7] and data_in[0] active, [7] has priority
        #10;
        tb_data_in = 8'b00000111; // data_in[2], [1], [0] active, [2] has priority
        #10;

        // No input active
        tb_data_in = 8'b00000000;
        #10;

        $finish; // End simulation
    end

    // Dump VCD for waveform viewing

    initial begin
        $dumpfile("encoder.vcd");
        $dumpvars(0, tb_encoder); // Dump all signals in the current scope
    end

    // Display simulation results (optional)
    always @* begin

        $display("Time: %0t, Data_in: %b, Encoded_out: %b, Valid_out: %b",
                 $time, tb_data_in, tb_encoded_out, tb_valid_out);
    end
endmodule

fromBK/sv_class/priority_encoder/encoder.vcd
$date
	Mon Sep 22 16:05:31 2025
$end
$version
	Icarus Verilog
$end
$timescale
	1ps
$end
$scope module tb_encoder $end
$var wire 1 ! tb_valid_out $end
$var wire 3 " tb_encoded_out [2:0] $end
$var reg 8 # tb_data_in [7:0] $end
$scope module dut $end
$var wire 8 $ data_in [7:0] $end
$var reg 3 % encoded_out [2:0] $end
$var reg 1 ! valid_out $end
$upscope $end
$upscope $end
$enddefinitions $end
#0
$dumpvars
b0 %
b0 $
b0 #
b0 "
0!
$end
#10000
1!
b1 #
b1 $
#20000
b1 "
b1 %
1!
b10 #
b10 $
#30000
1!
b10 "
b10 %
b100 #
b100 $
#40000
1!
b11 "
b11 %
b1000 #
b1000 $
#50000
1!
b100 "
b100 %
b10000 #
b10000 $
#60000
1!
b101 "
b101 %
b100000 #
b100000 $
#70000
1!
b110 "
b110 %
b1000000 #
b1000000 $
#80000
1!
b111 "
b111 %
b10000000 #
b10000000 $
#90000
1!
b111 "
b111 %
b10000001 #
b10000001 $
#100000
1!
b10 "
b10 %
b111 #
b111 $
#110000
0!
b0 "
b0 %
b0 #
b0 $
