fromBK/sv_class/MOD14_counter/MOD14_counter.v
// MOD 14 Counter Module

module mod14_counter (
    input clk,
    input rst_n, // Active-low reset
    output reg [3:0] count
);

always @(posedge clk or negedge rst_n) begin

    if (!rst_n) begin
        count <= 4'd0; // Reset to 0
    end else begin
        if (count == 4'd13) begin
            count <= 4'd0; // Reset to 0 after reaching 13
        end else begin
            count <= count + 4'd1; // Increment counter
        end
    end
end

endmodule

fromBK/sv_class/MOD14_counter/tb_MOD14_counter.v
// Testbench for MOD 14 Counter

module tb_mod14_counter;
    // Declare signals
    reg clk;
    reg rst_n;
    wire [3:0] count;

    // Instantiate the Device Under Test (DUT)
    mod14_counter DUT (
        .clk(clk),
        .rst_n(rst_n),
        .count(count)
    );

    // Clock generation
    initial begin
	  clk = 0;
	  forever  #5 clk = ~clk; // 10ns period (5ns high, 5ns low)
    end


    // Test stimulus and dumpvars
    initial begin
        // Dump VCD file for waveform viewing
        $dumpfile("mod14_counter.vcd");
        $dumpvars(0, tb_mod14_counter); // Dump all variables in the testbench and its hierarchy

        // Initialize inputs
        clk = 0;
        rst_n = 0; // Assert reset
        #10; // Hold reset for 10ns
        rst_n = 1; // De-assert reset

        // Monitor counter value
        $monitor("Time = %0t, Reset = %b, Count = %d", $time, rst_n, count);

        // Run simulation for a few cycles
        repeat (30) @(posedge clk); // Run for 30 clock cycles

        $finish; // End simulation
    end

endmodule

fromBK/sv_class/MOD14_counter/mod14_counter.vcd
$date
	Fri Sep 19 15:24:17 2025
$end
$version
	Icarus Verilog
$end
$timescale
	1s
$end
$scope module tb_mod14_counter $end
$var wire 4 ! count [3:0] $end
$var reg 1 " clk $end
$var reg 1 # rst_n $end
$scope module DUT $end
$var wire 1 " clk $end
$var wire 1 # rst_n $end
$var reg 4 $ count [3:0] $end
$upscope $end
$upscope $end
$enddefinitions $end
#0
$dumpvars
b0 $
0#
0"
b0 !
$end
#5
1"
#10
0"
1#
#15
b1 !
b1 $
1"
#20
0"
#25
b10 !
b10 $
1"
#30
0"
#35
b11 !
b11 $
1"
#40
0"
#45
b100 !
b100 $
1"
#50
0"
#55
b101 !
b101 $
1"
#60
0"
#65
b110 !
b110 $
1"
#70
0"
#75
b111 !
b111 $
1"
#80
0"
#85
b1000 !
b1000 $
1"
#90
0"
#95
b1001 !
b1001 $
1"
#100
0"
#105
b1010 !
b1010 $
1"
#110
0"
#115
b1011 !
b1011 $
1"
#120
0"
#125
b1100 !
b1100 $
1"
#130
0"
#135
b1101 !
b1101 $
1"
#140
0"
#145
b0 !
b0 $
1"
#150
0"
#155
b1 !
b1 $
1"
#160
0"
#165
b10 !
b10 $
1"
#170
0"
#175
b11 !
b11 $
1"
#180
0"
#185
b100 !
b100 $
1"
#190
0"
#195
b101 !
b101 $
1"
#200
0"
#205
b110 !
b110 $
1"
#210
0"
#215
b111 !
b111 $
1"
#220
0"
#225
b1000 !
b1000 $
1"
#230
0"
#235
b1001 !
b1001 $
1"
#240
0"
#245
b1010 !
b1010 $
1"
#250
0"
#255
b1011 !
b1011 $
1"
#260
0"
#265
b1100 !
b1100 $
1"
#270
0"
#275
b1101 !
b1101 $
1"
#280
0"
#285
b0 !
b0 $
1"
#290
0"
#295
b1 !
b1 $
1"
#300
0"
#305
b10 !
b10 $
1"
