fromBK/sv_class/test_counter/test.v
module DFF (
	input clk,
	input d,
	input rst,   // active-low asyn reset
	output reg q,
	output q_bar
	);

	assign q_bar = ~q;

	always @ (negedge clk or negedge rst) begin
		if (!rst) begin
			q <= 1'b0;
		end else begin
			q <= d;
		end
	end

endmodule

module NAND (
	input A, B, C, D,
	output y);

	assign y = ~(A & B & C & D);
endmodule

module DFF_tb;

	reg clk;
	reg rst;
	wire q1, q1_bar;
	wire q2, q2_bar;
	wire q3, q3_bar;
	wire q4, q4_bar;
	wire y;

	DFF DFF1(
		.clk(clk),
		.d(q1_bar),
		.rst(rst),
		.q(q1),
		.q_bar(q1_bar)
	);

	DFF DFF2(
		.clk(q1),
		.d(q2_bar),
		.rst(rst),
		.q(q2),
		.q_bar(q2_bar)
	);

	DFF DFF3(
		.clk(q2),
		.d(q3_bar),
		.rst(rst),
		.q(q3),
		.q_bar(q3_bar)
	);

	DFF DFF4(
		.clk(q3),
		.d(q4_bar),
		.rst(rst),
		.q(q4),
		.q_bar(q4_bar)
	);

	NAND DUT(
		.A(q4),
		.B(q3),
		.C(q2),
		.D(q1_bar),
		.y(y)
	);
		
	initial begin
		clk = 0;
		forever #10 clk = ~clk;
	end

	initial  begin
		rst <= 0;
		#10;
		rst <= 1;		

		$monitor("Time:%t | Reset:%b | NAND Y:%b | Q1=%b | Q2:%b | Q3:%b | Q4:%b",$time,rst,y,q1,q2,q3,q4);
		#500;
		$finish;
	end

	always @ (!y) begin
		rst <= 0;
		#10 rst <= 1;
	end

	initial begin
		$dumpfile("test.vcd");
		$dumpvars(0, DFF_tb);
	end
endmodule

fromBK/sv_class/test_counter/test.vcd
$date
	Wed Sep 24 11:21:30 2025
$end
$version
	Icarus Verilog
$end
$timescale
	1s
$end
$scope module DFF_tb $end
$var wire 1 ! y $end
$var wire 1 " q4_bar $end
$var wire 1 # q4 $end
$var wire 1 $ q3_bar $end
$var wire 1 % q3 $end
$var wire 1 & q2_bar $end
$var wire 1 ' q2 $end
$var wire 1 ( q1_bar $end
$var wire 1 ) q1 $end
$var reg 1 * clk $end
$var reg 1 + rst $end
$scope module DFF1 $end
$var wire 1 * clk $end
$var wire 1 ( d $end
$var wire 1 ( q_bar $end
$var wire 1 + rst $end
$var reg 1 ) q $end
$upscope $end
$scope module DFF2 $end
$var wire 1 ) clk $end
$var wire 1 & d $end
$var wire 1 & q_bar $end
$var wire 1 + rst $end
$var reg 1 ' q $end
$upscope $end
$scope module DFF3 $end
$var wire 1 ' clk $end
$var wire 1 $ d $end
$var wire 1 $ q_bar $end
$var wire 1 + rst $end
$var reg 1 % q $end
$upscope $end
$scope module DFF4 $end
$var wire 1 % clk $end
$var wire 1 " d $end
$var wire 1 " q_bar $end
$var wire 1 + rst $end
$var reg 1 # q $end
$upscope $end
$scope module DUT $end
$var wire 1 # A $end
$var wire 1 % B $end
$var wire 1 ' C $end
$var wire 1 ( D $end
$var wire 1 ! y $end
$upscope $end
$upscope $end
$enddefinitions $end
#0
$dumpvars
0+
0*
0)
1(
0'
1&
0%
1$
0#
1"
1!
$end
#10
1+
1*
#20
0(
1)
0*
#30
1*
#40
0&
1'
1(
0)
0*
#50
1*
#60
0(
1)
0*
#70
1*
#80
0$
1%
1&
0'
1(
0)
0*
#90
1*
#100
0(
1)
0*
#110
1*
#120
0&
1'
1(
0)
0*
#130
1*
#140
0(
1)
0*
#150
1*
#160
0"
1#
1$
0%
1&
0'
1(
0)
0*
#170
1*
#180
0(
1)
0*
#190
1*
#200
0&
1'
1(
0)
0*
#210
1*
#220
0(
1)
0*
#230
1*
#240
0$
1%
1&
0'
1(
0)
0*
#250
1*
#260
0(
1)
0*
#270
1*
#280
1$
1"
0%
0#
0+
1!
1&
0'
1(
0)
0*
#290
1+
1*
#300
0(
1)
0*
#310
1*
#320
0&
1'
1(
0)
0*
#330
1*
#340
0(
1)
0*
#350
1*
#360
0$
1%
1&
0'
1(
0)
0*
#370
1*
#380
0(
1)
0*
#390
1*
#400
0&
1'
1(
0)
0*
#410
1*
#420
0(
1)
0*
#430
1*
#440
0"
1#
1$
0%
1&
0'
1(
0)
0*
#450
1*
#460
0(
1)
0*
#470
1*
#480
0&
1'
1(
0)
0*
#490
1*
#500
0(
1)
0*
