fromBK/sv_class/decoder/decoder.v
// 3-to-8 Decoder Module

module decoder_3_to_8(
    input [2:0] in,
    input enable,
    output reg [7:0] out
);

always @(in or enable) begin

    if (enable) begin
        case (in)
            3'b000: out = 8'b00000001;
            3'b001: out = 8'b00000010;
            3'b010: out = 8'b00000100;
            3'b011: out = 8'b00001000;
            3'b100: out = 8'b00010000;
            3'b101: out = 8'b00100000;
            3'b110: out = 8'b01000000;
            3'b111: out = 8'b10000000;
            default: out = 8'b00000000; // Should not occur with 3-bit input
        endcase
    end else begin
        out = 8'b00000000; // All outputs low when disabled
    end
end

endmodule

fromBK/sv_class/decoder/decoder_tb.v
// Testbench for 3-to-8 Decoder
module testbench_decoder_3_to_8;

integer i;

    // Inputs
    reg [2:0] tb_in;
    reg tb_enable;

    // Outputs
    wire [7:0] tb_out;

    // Instantiate the Unit Under Test (UUT)
    decoder_3_to_8 uut (
        .in(tb_in),
        .enable(tb_enable),
        .out(tb_out)
    );

    initial begin

        // Dump waves for simulation visualization
        $dumpfile("decoder_waveform.vcd");
        $dumpvars(0, testbench_decoder_3_to_8); // Dump all signals in this module and its hierarchy

        // Initialize inputs
        tb_enable = 1'b0;
        tb_in = 3'b000;
        #10; // Wait for initial state to settle

        // Test with enable off
        $display("--- Testing with Enable OFF ---");
        tb_enable = 1'b0;
        for (i = 0; i < 8; i = i + 1) begin
            tb_in = i;
            #10;
            $display("Time: %0t, Input: %b, Enable: %b, Output: %b", $time, tb_in, tb_enable, tb_out);
        end

        // Test with enable on
        $display("--- Testing with Enable ON ---");
        tb_enable = 1'b1;
	tb_in = 3'b000;
        for (i = 0; i < 8; i = i + 1) begin
            tb_in = i;
            #10;
	    $display("Time: %0t, Input: %b, Enable: %b, Output: %b", $time, tb_in, tb_enable, tb_out);
        end

        // Finish simulation
        $finish;
    end

endmodule

fromBK/sv_class/decoder/decoder_waveform.vcd
$date
	Thu Sep 11 13:42:59 2025
$end
$version
	Icarus Verilog
$end
$timescale
	1s
$end
$scope module testbench_decoder_3_to_8 $end
$var wire 8 ! tb_out [7:0] $end
$var reg 1 " tb_enable $end
$var reg 3 # tb_in [2:0] $end
$var integer 32 $ i [31:0] $end
$scope module uut $end
$var wire 1 " enable $end
$var wire 3 % in [2:0] $end
$var reg 8 & out [7:0] $end
$upscope $end
$upscope $end
$enddefinitions $end
#0
$dumpvars
b0 &
b0 %
bx $
b0 #
0"
b0 !
$end
#10
b0 $
#20
b1 #
b1 %
b1 $
#30
b10 #
b10 %
b10 $
#40
b11 #
b11 %
b11 $
#50
b100 #
b100 %
b100 $
#60
b101 #
b101 %
b101 $
#70
b110 #
b110 %
b110 $
#80
b111 #
b111 %
b111 $
#90
b1 !
b1 &
b0 #
b0 %
1"
b0 $
#100
b10 !
b10 &
b1 #
b1 %
b1 $
#110
b100 !
b100 &
b10 #
b10 %
b10 $
#120
b1000 !
b1000 &
b11 #
b11 %
b11 $
#130
b10000 !
b10000 &
b100 #
b100 %
b100 $
#140
b100000 !
b100000 &
b101 #
b101 %
b101 $
#150
b1000000 !
b1000000 &
b110 #
b110 %
b110 $
#160
b10000000 !
b10000000 &
b111 #
b111 %
b111 $
#170
b1000 $
