fromBK/sv_class/MOD6_counter/MOD6_counter.v
// MOD 6 Counter Module

module mod6_counter (
    input clk,
    input rst_n, // Active-low reset
    output reg [2:0] count
);

always @(posedge clk or negedge rst_n) begin

    if (!rst_n) begin
        count <= 3'd0; // Reset to 0
    end else begin
        if (count == 3'd5) begin
            count <= 3'd0; // Reset to 0 after reaching 13
        end else begin
            count <= count + 3'd1; // Increment counter
        end
    end
end

endmodule

fromBK/sv_class/MOD6_counter/MOD6_counter_tb.v
// Testbench for MOD6 Counter

module tb_mod6_counter;
    // Declare signals
    reg clk;
    reg rst_n;
    wire [2:0] count;

    // Instantiate the Device Under Test (DUT)
    mod6_counter DUT (
        .clk(clk),
        .rst_n(rst_n),
        .count(count)
    );

    // Clock generation
    initial begin
	  clk = 0;
	  forever  #5 clk = ~clk; // 10ns period (5ns high, 5ns low)
    end

    // Test stimulus and dumpvars
    initial begin
        // Dump VCD file for waveform viewing
        $dumpfile("mod6counter.vcd");
        $dumpvars(0, tb_mod6_counter); // Dump all variables in the testbench and its hierarchy

        // Initialize inputs
        clk = 0;
        rst_n = 0; // Assert reset
        #10; // Hold reset for 10ns
        rst_n = 1; // De-assert reset

        // Monitor counter value
        $monitor("Time = %0t, Reset = %b, Count = %d", $time, rst_n, count);

        // Run simulation for a few cycles
        repeat (30) @(posedge clk); // Run for 30 clock cycles

        $finish; // End simulation
    end

endmodule

fromBK/sv_class/MOD6_counter/mod6counter.vcd
$date
	Fri Sep 19 15:52:39 2025
$end
$version
	Icarus Verilog
$end
$timescale
	1s
$end
$scope module tb_mod6_counter $end
$var wire 3 ! count [2:0] $end
$var reg 1 " clk $end
$var reg 1 # rst_n $end
$scope module DUT $end
$var wire 1 " clk $end
$var wire 1 # rst_n $end
$var reg 3 $ count [2:0] $end
$upscope $end
$upscope $end
$enddefinitions $end
#0
$dumpvars
b0 $
0#
0"
b0 !
$end
#5
1"
#10
0"
1#
#15
b1 !
b1 $
1"
#20
0"
#25
b10 !
b10 $
1"
#30
0"
#35
b11 !
b11 $
1"
#40
0"
#45
b100 !
b100 $
1"
#50
0"
#55
b101 !
b101 $
1"
#60
0"
#65
b0 !
b0 $
1"
#70
0"
#75
b1 !
b1 $
1"
#80
0"
#85
b10 !
b10 $
1"
#90
0"
#95
b11 !
b11 $
1"
#100
0"
#105
b100 !
b100 $
1"
#110
0"
#115
b101 !
b101 $
1"
#120
0"
#125
b0 !
b0 $
1"
#130
0"
#135
b1 !
b1 $
1"
#140
0"
#145
b10 !
b10 $
1"
#150
0"
#155
b11 !
b11 $
1"
#160
0"
#165
b100 !
b100 $
1"
#170
0"
#175
b101 !
b101 $
1"
#180
0"
#185
b0 !
b0 $
1"
#190
0"
#195
b1 !
b1 $
1"
#200
0"
#205
b10 !
b10 $
1"
#210
0"
#215
b11 !
b11 $
1"
#220
0"
#225
b100 !
b100 $
1"
#230
0"
#235
b101 !
b101 $
1"
#240
0"
#245
b0 !
b0 $
1"
#250
0"
#255
b1 !
b1 $
1"
#260
0"
#265
b10 !
b10 $
1"
#270
0"
#275
b11 !
b11 $
1"
#280
0"
#285
b100 !
b100 $
1"
#290
0"
#295
b101 !
b101 $
1"
#300
0"
#305
b0 !
b0 $
1"
