fromBK/sv_class/MUX/MUX.v
module mux_8_to_1(
	input [7:0] a_i,
	input [2:0] s_i,
	output reg y_o
);

always @(*) begin
	case(s_i)
		3'b000: y_o = a_i[0];
		3'b001: y_o = a_i[1];
		3'b010: y_o = a_i[2];
		3'b011: y_o = a_i[3];
		3'b100: y_o = a_i[4];
		3'b101: y_o = a_i[5];
		3'b110: y_o = a_i[6];
		3'b111: y_o = a_i[7];
		default: y_o = 1'b0;
	endcase
end
endmodule

fromBK/sv_class/MUX/MUX_tb.v
module mux_8_to_1_tb;
	reg [7:0] a_i;
	reg [2:0] s_i;
	wire y_o;
	integer i;

	mux_8_to_1 DUT(
		.a_i(a_i),
		.s_i(s_i),
		.y_o(y_o)
	);

	initial begin
		$dumpfile("test.vcd");
		$dumpvars(0,mux_8_to_1_tb);
	end

	initial begin
		a_i = 8'b00100101;	
		for (i=0;i<=7;i+=1) begin
		s_i=i;
		#10;
		$display("Time: %0t, Input: %b, Selector: %b, Output: %b", $time, a_i, s_i, y_o);
		end
	$finish;
	end
	endmodule

fromBK/sv_class/MUX/test.vcd
$date
	Fri Sep 12 11:26:04 2025
$end
$version
	Icarus Verilog
$end
$timescale
	1s
$end
$scope module mux_8_to_1_tb $end
$var wire 1 ! y_o $end
$var reg 8 " a_i [7:0] $end
$var reg 3 # s_i [2:0] $end
$var integer 32 $ i [31:0] $end
$scope module DUT $end
$var wire 8 % a_i [7:0] $end
$var wire 3 & s_i [2:0] $end
$var reg 1 ! y_o $end
$upscope $end
$upscope $end
$enddefinitions $end
#0
$dumpvars
b0 &
b100101 %
b0 $
b0 #
b100101 "
1!
$end
#10
0!
b1 #
b1 &
b1 $
#20
1!
b10 #
b10 &
b10 $
#30
0!
b11 #
b11 &
b11 $
#40
b100 #
b100 &
b100 $
#50
1!
b101 #
b101 &
b101 $
#60
0!
b110 #
b110 &
b110 $
#70
b111 #
b111 &
b111 $
#80
b1000 $
