fromBK/sv_class/test/test.v
module test (
	input wire a_i,
	input wire b_i,
	input wire c_i,
	input wire d_i,
	output wire y_o
);

assign y_o = ~((a_i | b_i) & (c_i & d_i));


endmodule

fromBK/sv_class/test/test_tb.v
module test_tb;

	integer i;
	reg a, b, c, d;
	wire y;

	test DUT (
		.a_i(a),
		.b_i(b),
		.c_i(c),
		.d_i(d),
		.y_o(y)
	);

	initial begin 
		$dumpfile("test.vcd");
		$dumpvars(0,test_tb);

		for (i=0;i<=15;i+=1) begin
			a=(i>>3)&1;
			b=(i>>2)&1;
			c=(i>>1)&1;
			d=i &1;
			#25

			$display("Input: A=%0b, B=%0b, C=%0b, D=%0b", a, b, c, d);
			$display("Output: %0b", y);

		end
		$finish;
	end
endmodule

fromBK/sv_class/test/test.vcd
$date
	Wed Sep 10 16:36:29 2025
$end
$version
	Icarus Verilog
$end
$timescale
	1s
$end
$scope module test_tb $end
$var wire 1 ! y $end
$var reg 1 " a $end
$var reg 1 # b $end
$var reg 1 $ c $end
$var reg 1 % d $end
$var integer 32 & i [31:0] $end
$scope module DUT $end
$var wire 1 " a_i $end
$var wire 1 # b_i $end
$var wire 1 $ c_i $end
$var wire 1 % d_i $end
$var wire 1 ! y_o $end
$upscope $end
$upscope $end
$enddefinitions $end
#0
$dumpvars
b0 &
0%
0$
0#
0"
1!
$end
#25
1%
b1 &
#50
0%
1$
b10 &
#75
1%
b11 &
#100
0%
0$
1#
b100 &
#125
1%
b101 &
#150
0%
1$
b110 &
#175
0!
1%
b111 &
#200
1!
0%
0$
0#
1"
b1000 &
#225
1%
b1001 &
#250
0%
1$
b1010 &
#275
0!
1%
b1011 &
#300
1!
0%
0$
1#
b1100 &
#325
1%
b1101 &
#350
0%
1$
b1110 &
#375
0!
1%
b1111 &
#400
b10000 &
