fromBK/sv_class/counter/4bit_counter.v
module counter_4bit (

    input clk,
    input rstn, // Active-low reset
    output reg [3:0] count_out

);

always @(posedge clk or negedge rstn) begin

    if (!rstn) begin // If reset is active (low)
        count_out <= 4'b0000; // Reset counter to 0
    end else begin
        count_out <= count_out + 1; // Increment counter
    end
end

endmodule

fromBK/sv_class/counter/4bit_counter_tb.v
module tb_counter_4bit;

    // Declare testbench signals
    reg clk;
    reg rstn;
    wire [3:0] count_out;

    // Instantiate the Unit Under Test (UUT)
    counter_4bit dut (
        .clk(clk),
        .rstn(rstn),
        .count_out(count_out)
    );

    // Clock generation
    initial begin
        clk = 0;
        forever #5 clk = ~clk; // Toggle clock every 5ns (10ns period)
    end

    // Stimulus generation
    initial begin

        // Dump waveforms for simulation analysis
        $dumpfile("tb_counter.vcd");
        $dumpvars(0, tb_counter_4bit);
    
	    // Initial conditions
        rstn = 0; // Assert reset
        #20;      // Hold reset for 20ns
        // rstn = 1;
        // #200;    // Allow counting for 100ns
        // rstn = 0; // Assert reset again
	rstn = 1;
	#300
        // #20;      // Hold reset
        //  rstn = 1; // Deassert reset
        // #50;      // Allow more counting
        $finish;  // End simulation
    end

    // Monitor and display output
    initial begin
        $monitor("Time=%0tns, clk=%0b, rstn=%0b, count_out=%0d", $time, clk, rstn, count_out);
    end

endmodule

fromBK/sv_class/counter/tb_counter.vcd
$date
	Thu Sep 11 11:27:56 2025
$end
$version
	Icarus Verilog
$end
$timescale
	1s
$end
$scope module tb_counter_4bit $end
$var wire 4 ! count_out [3:0] $end
$var reg 1 " clk $end
$var reg 1 # rstn $end
$scope module dut $end
$var wire 1 " clk $end
$var wire 1 # rstn $end
$var reg 4 $ count_out [3:0] $end
$upscope $end
$upscope $end
$enddefinitions $end
#0
$dumpvars
b0 $
0#
0"
b0 !
$end
#5
1"
#10
0"
#15
1"
#20
0"
1#
#25
b1 !
b1 $
1"
#30
0"
#35
b10 !
b10 $
1"
#40
0"
#45
b11 !
b11 $
1"
#50
0"
#55
b100 !
b100 $
1"
#60
0"
#65
b101 !
b101 $
1"
#70
0"
#75
b110 !
b110 $
1"
#80
0"
#85
b111 !
b111 $
1"
#90
0"
#95
b1000 !
b1000 $
1"
#100
0"
#105
b1001 !
b1001 $
1"
#110
0"
#115
b1010 !
b1010 $
1"
#120
0"
#125
b1011 !
b1011 $
1"
#130
0"
#135
b1100 !
b1100 $
1"
#140
0"
#145
b1101 !
b1101 $
1"
#150
0"
#155
b1110 !
b1110 $
1"
#160
0"
#165
b1111 !
b1111 $
1"
#170
0"
#175
b0 !
b0 $
1"
#180
0"
#185
b1 !
b1 $
1"
#190
0"
#195
b10 !
b10 $
1"
#200
0"
#205
b11 !
b11 $
1"
#210
0"
#215
b100 !
b100 $
1"
#220
0"
#225
b101 !
b101 $
1"
#230
0"
#235
b110 !
b110 $
1"
#240
0"
#245
b111 !
b111 $
1"
#250
0"
#255
b1000 !
b1000 $
1"
#260
0"
#265
b1001 !
b1001 $
1"
#270
0"
#275
b1010 !
b1010 $
1"
#280
0"
#285
b1011 !
b1011 $
1"
#290
0"
#295
b1100 !
b1100 $
1"
#300
0"
#305
b1101 !
b1101 $
1"
#310
0"
#315
b1110 !
b1110 $
1"
