fromBK/sv_class/votercircuit/voter.v
module voter(
	input wire a_i,
	input wire b_i,
	input wire c_i,
	output wire v_o
	);

assign v_o = (a_i & b_i) | (a_i & c_i) | (b_i & c_i);

endmodule

fromBK/sv_class/votercircuit/voter_tb.v
module votertb;
	
	integer i;

	reg  a, b, c;	// UUT input
	wire v;		// UUT output

	voter UUT (
		.a_i(a),
		.b_i(b),
		.c_i(c),
		.v_o(v)
	);

	initial begin
		$dumpfile("voter_tb.vcd");
		$dumpvars(0,votertb);


		for (i=0; i<8; i+=1) begin
			a=(i>>2) &1;
			b=(i>>1) &1;
			c=i &1;
			#20

			$display("Input: A=%0b, B=%0b, C=%0b", a, b, c);
			$display("Output: v=%0b", v);
		end

		$finish;
	end
endmodule

fromBK/sv_class/votercircuit/voter_tb.vcd
$date
	Fri Sep 19 15:05:54 2025
$end
$version
	Icarus Verilog
$end
$timescale
	1s
$end
$scope module votertb $end
$var wire 1 ! v $end
$var reg 1 " a $end
$var reg 1 # b $end
$var reg 1 $ c $end
$var integer 32 % i [31:0] $end
$scope module UUT $end
$var wire 1 " a_i $end
$var wire 1 # b_i $end
$var wire 1 $ c_i $end
$var wire 1 ! v_o $end
$upscope $end
$upscope $end
$enddefinitions $end
#0
$dumpvars
b0 %
0$
0#
0"
0!
$end
#20
1$
b1 %
#40
0$
1#
b10 %
#60
1!
1$
b11 %
#80
0!
0$
0#
1"
b100 %
#100
1!
1$
b101 %
#120
0$
1#
b110 %
#140
1$
b111 %
#160
b1000 %
